{
    "status": 1,
    "complete": 1,
    "list": {
        "2573820237": {
            "item_id": "2573820237",
            "resolved_id": "2573820237",
            "given_url": "https://vc.ru/future/65907-paradoks-procvetaniya-neobychnye-metody-s-pomoshchyu-kotoryh-mozhno-likvidirovat-nishchetu-v-samyh-bednyh-i-otstalyh-stranah",
            "given_title": "\u00ab\u041f\u0430\u0440\u0430\u0434\u043e\u043a\u0441 \u043f\u0440\u043e\u0446\u0432\u0435\u0442\u0430\u043d\u0438\u044f\u00bb: \u043d\u0435\u043e\u0431\u044b\u0447\u043d\u044b\u0435 \u043c\u0435\u0442\u043e\u0434\u044b, \u0441 \u043f\u043e\u043c\u043e\u0449\u044c\u044e \u043a\u043e\u0442\u043e\u0440\u044b\u0445 \u043c\u043e\u0436\u043d\u043e \u043b\u0438\u043a\u0432\u0438\u0434\u0438\u0440\u043e",
            "favorite": "0",
            "status": "0",
            "time_added": "1556480407",
            "time_updated": "1556480421",
            "time_read": "0",
            "time_favorited": "0",
            "sort_id": 0,
            "resolved_title": "\u00ab\u041f\u0430\u0440\u0430\u0434\u043e\u043a\u0441 \u043f\u0440\u043e\u0446\u0432\u0435\u0442\u0430\u043d\u0438\u044f\u00bb: \u043d\u0435\u043e\u0431\u044b\u0447\u043d\u044b\u0435 \u043c\u0435\u0442\u043e\u0434\u044b, \u0441 \u043f\u043e\u043c\u043e\u0449\u044c\u044e \u043a\u043e\u0442\u043e\u0440\u044b\u0445 \u043c\u043e\u0436\u043d\u043e \u043b\u0438\u043a\u0432\u0438\u0434\u0438\u0440\u043e\u0432\u0430\u0442\u044c \u043d\u0438\u0449\u0435\u0442\u0443 \u0432 \u0441\u0430\u043c\u044b\u0445 \u0431\u0435\u0434\u043d\u044b\u0445 \u0438 \u043e\u0442\u0441\u0442\u0430\u043b\u044b\u0445 \u0441\u0442\u0440\u0430\u043d\u0430\u0445",
            "resolved_url": "https://vc.ru/future/65907-paradoks-procvetaniya-neobychnye-metody-s-pomoshchyu-kotoryh-mozhno-likvidirovat-nishchetu-v-samyh-bednyh-i-otstalyh-stranah",
            "excerpt": "\u0420\u0435\u0434\u0430\u043a\u0446\u0438\u044f \u0441\u0435\u0440\u0432\u0438\u0441\u0430 MakeRight.ru \u043f\u043e\u0434\u0433\u043e\u0442\u043e\u0432\u0438\u043b\u0430 \u043a\u043b\u044e\u0447\u0435\u0432\u044b\u0435 \u0438\u0434\u0435\u0438 \u043d\u0435 \u0438\u0437\u0434\u0430\u043d\u043d\u043e\u0433\u043e \u043d\u0430 \u0440\u0443\u0441\u0441\u043a\u043e\u043c \u0431\u0435\u0441\u0442\u0441\u0435\u043b\u043b\u0435\u0440\u0430 \u00ab\u041f\u0430\u0440\u0430\u0434\u043e\u043a\u0441 \u043f\u0440\u043e\u0446\u0432\u0435\u0442\u0430\u043d\u0438\u044f\u00bb \u041a\u043b\u0435\u0439\u0442\u043e\u043d\u0430 \u041c.",
            "is_article": "1",
            "is_index": "0",
            "has_video": "0",
            "has_image": "0",
            "word_count": "4872",
            "lang": "ru",
            "time_to_read": 27,
            "amp_url": "https://vc.ru/amp/65907",
            "top_image_url": "https://vc.ru/cover/fb/c/65907/1556365144/cover.jpg",
            "domain_metadata": {
                "name": "\u0421\u0442\u0430\u0440\u0442\u0430\u043f\u044b \u0438 \u0431\u0438\u0437\u043d\u0435\u0441",
                "logo": "https://logo.clearbit.com/vc.ru?size=800",
                "greyscale_logo": "https://logo.clearbit.com/vc.ru?size=800&greyscale=true"
            },
            "listen_duration_estimate": 1886
        },
        "2574456102": {
            "item_id": "2574456102",
            "resolved_id": "2574456102",
            "given_url": "https://devblogs.microsoft.com/odata/supercharging-asp-net-core-api-with-odata/",
            "given_title": "Supercharging ASP.NET Core API with OData | OData",
            "favorite": "0",
            "status": "0",
            "time_added": "1556480221",
            "time_updated": "1556480246",
            "time_read": "0",
            "time_favorited": "0",
            "sort_id": 1,
            "resolved_title": "Supercharging ASP.NET Core API with OData",
            "resolved_url": "https://devblogs.microsoft.com/odata/supercharging-asp-net-core-api-with-odata/",
            "excerpt": "In this article, I\u2019m going to show you how you can supercharge your existing ASP.NET Core APIs with OData to provide better experience for your API consumers with only 4 lines of code.",
            "is_article": "1",
            "is_index": "0",
            "has_video": "0",
            "has_image": "0",
            "word_count": "1058",
            "lang": "en",
            "time_to_read": 5,
            "top_image_url": "https://devblogs.microsoft.com/odata/wp-content/uploads/sites/23/2019/04/aspnetcorewithodata-1.jpg",
            "listen_duration_estimate": 410
        },
        "2321482648": {
            "item_id": "2321482648",
            "resolved_id": "2321482648",
            "given_url": "https://prodotnetmemory.com/",
            "given_title": "Pro .NET Memory Management",
            "favorite": "0",
            "status": "0",
            "time_added": "1554407446",
            "time_updated": "1554407489",
            "time_read": "0",
            "time_favorited": "0",
            "sort_id": 2,
            "resolved_title": "Pro .NET Memory Management",
            "resolved_url": "https://prodotnetmemory.com/",
            "excerpt": "Become a better .NET programmer, gain the knowledge about memory management! Understand how and why memory is managed by .",
            "is_article": "0",
            "is_index": "1",
            "has_video": "0",
            "has_image": "1",
            "word_count": "845",
            "lang": "en",
            "time_to_read": 4,
            "listen_duration_estimate": 327
        },
        "2515811370": {
            "item_id": "2515811370",
            "resolved_id": "2515811370",
            "given_url": "https://felix-kling.de/js-loose-comparison/",
            "given_title": "JavaScript loose comparison (==) step by step",
            "favorite": "0",
            "status": "0",
            "time_added": "1553595381",
            "time_updated": "1553595409",
            "time_read": "0",
            "time_favorited": "0",
            "sort_id": 3,
            "resolved_title": "JavaScript \"loose\" comparison step by step",
            "resolved_url": "https://felix-kling.de/js-loose-comparison/",
            "excerpt": "When you start learning JavaScript, you will likely read about preferring to use === over == to compare values. But why?",
            "is_article": "0",
            "is_index": "0",
            "has_video": "0",
            "has_image": "0",
            "word_count": "87",
            "lang": "",
            "listen_duration_estimate": 34
        },
        "2148956": {
            "item_id": "2148956",
            "resolved_id": "2498934757",
            "given_url": "https://www.google.com/",
            "given_title": "Google",
            "favorite": "0",
            "status": "0",
            "time_added": "1552151772",
            "time_updated": "1552151773",
            "time_read": "0",
            "time_favorited": "0",
            "sort_id": 4,
            "resolved_title": "",
            "resolved_url": "https://www.google.com/logos/doodles/2019/steve-irwins-57th-birthday-5182163212304384.2-2xa.gif",
            "excerpt": "",
            "is_article": "0",
            "is_index": "0",
            "has_video": "0",
            "has_image": "2",
            "word_count": "0",
            "lang": "",
            "domain_metadata": {
                "name": "Google",
                "logo": "https://logo.clearbit.com/google.com?size=800",
                "greyscale_logo": "https://logo.clearbit.com/google.com?size=800&greyscale=true"
            },
            "listen_duration_estimate": 0
        },
        "2514784204": {
            "item_id": "2514784204",
            "resolved_id": "2514784204",
            "given_url": "https://scontent.fiev20-1.fna.fbcdn.net/v/t1.0-9/53287805_2051860671515938_7301143944467841024_n.jpg?_nc_cat=106&_nc_ht=scontent.fiev20-1.fna&oh=65698dc301146cbf1c16fda2325d4e28&oe=5D2803E3",
            "given_title": "53287805_2051860671515938_7301143944467841024_n.jpg (631\u00d7960)",
            "favorite": "0",
            "status": "0",
            "time_added": "1551982846",
            "time_updated": "1551982863",
            "time_read": "0",
            "time_favorited": "0",
            "sort_id": 5,
            "resolved_title": "",
            "resolved_url": "https://scontent.fiev20-1.fna.fbcdn.net/v/t1.0-9/53287805_2051860671515938_7301143944467841024_n.jpg?_nc_cat=106&_nc_ht=scontent.fiev20-1.fna&oh=65698dc301146cbf1c16fda2325d4e28&oe=5D2803E3",
            "excerpt": "",
            "is_article": "0",
            "is_index": "0",
            "has_video": "0",
            "has_image": "2",
            "word_count": "0",
            "lang": "",
            "listen_duration_estimate": 0
        },
        "2380018980": {
            "item_id": "2380018980",
            "resolved_id": "2380018980",
            "given_url": "https://eng.uber.com/analyzing-experiment-outcomes/",
            "given_title": "Analyzing Experiment Outcomes: Beyond Average Treatment Effects | Uber Engi",
            "favorite": "0",
            "status": "0",
            "time_added": "1550647550",
            "time_updated": "1550647584",
            "time_read": "0",
            "time_favorited": "0",
            "sort_id": 6,
            "resolved_title": "Analyzing Experiment Outcomes: Beyond Average Treatment Effects",
            "resolved_url": "https://eng.uber.com/analyzing-experiment-outcomes/",
            "excerpt": "At Uber, we test most new features and products with the help of experiments in order to understand and quantify their impact on our marketplace. The analysis of experimental results traditionally focuses on calculating average treatment effects (ATEs).",
            "is_article": "1",
            "is_index": "0",
            "has_video": "0",
            "has_image": "1",
            "word_count": "1982",
            "lang": "en",
            "time_to_read": 9,
            "top_image_url": "https://eng.uber.com/wp-content/uploads/2018/11/ETA-Header.png",
            "listen_duration_estimate": 767
        },
        "1284686839": {
            "item_id": "1284686839",
            "resolved_id": "1284686839",
            "given_url": "http://food-hunter.ru/polenta-s-rikottoi-shpinatom-i-gorgonzoloi.html",
            "given_title": "\u041f\u043e\u043b\u0435\u043d\u0442\u0430 \u0441 \u0440\u0438\u043a\u043e\u0442\u0442\u043e\u0439, \u0448\u043f\u0438\u043d\u0430\u0442\u043e\u043c \u0438 \u0433\u043e\u0440\u0433\u043e\u043d\u0437\u043e\u043b\u043e\u0439. \u0420\u0435\u0446\u0435\u043f\u0442 \u0441 \u0444\u043e\u0442\u043e",
            "favorite": "0",
            "status": "0",
            "time_added": "1550075890",
            "time_updated": "1550075936",
            "time_read": "0",
            "time_favorited": "0",
            "sort_id": 7,
            "resolved_title": "\u041f\u043e\u043b\u0435\u043d\u0442\u0430 \u0441 \u0440\u0438\u043a\u043e\u0442\u0442\u043e\u0439, \u0448\u043f\u0438\u043d\u0430\u0442\u043e\u043c \u0438 \u0433\u043e\u0440\u0433\u043e\u043d\u0437\u043e\u043b\u043e\u0439",
            "resolved_url": "http://food-hunter.ru/polenta-s-rikottoi-shpinatom-i-gorgonzoloi.html",
            "excerpt": "\u0421\u0435\u0433\u043e\u0434\u043d\u044f \u0445\u043e\u0447\u0443 \u043f\u043e\u0434\u0435\u043b\u0438\u0442\u044c\u0441\u044f \u0441 \u0432\u0430\u043c\u0438 \u0440\u0435\u0446\u0435\u043f\u0442\u043e\u043c, \u043a\u043e\u0442\u043e\u0440\u044b\u0439 \u0441\u0442\u0430\u043b \u0434\u043b\u044f \u043c\u0435\u043d\u044f \u0431\u0443\u043a\u0432\u0430\u043b\u044c\u043d\u043e \u043e\u0442\u043a\u0440\u044b\u0442\u0438\u0435\u043c.",
            "is_article": "1",
            "is_index": "0",
            "has_video": "0",
            "has_image": "0",
            "word_count": "400",
            "lang": "ru",
            "top_image_url": "http://food-hunter.ru/wp-content/uploads/2016/05/baked-polenta.jpg",
            "listen_duration_estimate": 155
        },
        "2488449951": {
            "item_id": "2488449951",
            "resolved_id": "2488449951",
            "given_url": "https://azure.microsoft.com/ru-ru/blog/benefits-of-using-azure-api-management-with-microservices/",
            "given_title": "Benefits of using Azure API Management with microservices | \u0411\u043b\u043e\u0433 | Microsof",
            "favorite": "0",
            "status": "0",
            "time_added": "1550046477",
            "time_updated": "1550128460",
            "time_read": "0",
            "time_favorited": "0",
            "sort_id": 8,
            "resolved_title": "Benefits of using Azure API Management with microservices",
            "resolved_url": "https://azure.microsoft.com/ru-ru/blog/benefits-of-using-azure-api-management-with-microservices/",
            "excerpt": "The IT industry is experiencing a shift from monolithic applications to microservices-based architectures. The benefits of this new approach include: Let\u2019s consider a simplified online store system.",
            "is_article": "1",
            "is_index": "0",
            "has_video": "0",
            "has_image": "1",
            "word_count": "980",
            "lang": "en",
            "time_to_read": 4,
            "top_image_url": "https://azurecomcdn.azureedge.net/mediahandler/acomblog/media/Default/blog/d4057126-035d-44b1-ba68-f7e3a1ebb695.png",
            "domain_metadata": {
                "name": "Microsoft",
                "logo": "https://logo.clearbit.com/microsoft.com?size=800",
                "greyscale_logo": "https://logo.clearbit.com/microsoft.com?size=800&greyscale=true"
            },
            "listen_duration_estimate": 379
        },
        "2473961286": {
            "item_id": "2473961286",
            "resolved_id": "2473961286",
            "given_url": "https://taplink.cc/karenskaya",
            "given_title": "@karenskaya | Taplink.cc",
            "favorite": "0",
            "status": "0",
            "time_added": "1548956023",
            "time_updated": "1548956038",
            "time_read": "0",
            "time_favorited": "0",
            "sort_id": 9,
            "resolved_title": "@karenskaya | taplink.cc",
            "resolved_url": "https://taplink.cc/karenskaya",
            "excerpt": "",
            "is_article": "0",
            "is_index": "1",
            "has_video": "0",
            "has_image": "0",
            "word_count": "0",
            "lang": "ru",
            "top_image_url": "https://scontent-arn2-1.cdninstagram.com/vp/1554bfe5076a577c360c994c3f30b883/5CE30915/t51.2885-19/10932565_1034705319876683_1507490747_a.jpg?_nc_ht=scontent-arn2-1.cdninstagram.com",
            "listen_duration_estimate": 0
        }
    },
    "error": null,
    "search_meta": {"search_type": "normal"},
    "since": 1556649837
}
